grai_source_fivetran/__init__.py
grai_source_fivetran/adapters.py
grai_source_fivetran/base.py
grai_source_fivetran/fivetran_api/__init__.py
grai_source_fivetran/fivetran_api/api_models.py
grai_source_fivetran/fivetran_api/main.py
grai_source_fivetran/loader.py
grai_source_fivetran/mock_tools.py
grai_source_fivetran/models.py
grai_source_fivetran/package_definitions.py
grai_source_fivetran/py.typed
grai_source_fivetran-0.1.2.dist-info/METADATA
grai_source_fivetran-0.1.2.dist-info/WHEEL
grai_source_fivetran-0.1.2.dist-info/RECORD
